{
  "actors": [
    {
      "id": 1,
      "name": "Munmro Labus",
      "picture": "https://picsum.photos/200/300",
      "occupation": "Web Developer III",
      "likes": 39,
      "description": "Lorem ipsum dolor sit amet, consectetur adipisicing elit. Assumenda dolor labore ullam sapiente recusandae voluptatibus! Eligendi consequuntur nesciunt totam aut?",
      "hobbies": [
        "Reading",
        "Dancing",
        "Watching movies"
      ]
    },
    {
      "id": 2,
      "name": "Cornall McPaik",
      "picture": "https://picsum.photos/200/300",
      "occupation": "Research Associate",
      "likes": 28,
      "description": "Lorem ipsum dolor sit amet, consectetur adipisicing elit. Assumenda dolor labore ullam sapiente recusandae voluptatibus! Eligendi consequuntur nesciunt totam aut?",
      "hobbies": [
        "Reading",
        "Dancing",
        "Watching movies"
      ]
    },
    {
      "id": 3,
      "name": "Yale Dykas",
      "picture": "https://picsum.photos/200/300",
      "occupation": "Software Engineer II",
      "likes": 17,
      "description": "Lorem ipsum dolor sit amet, consectetur adipisicing elit. Assumenda dolor labore ullam sapiente recusandae voluptatibus! Eligendi consequuntur nesciunt totam aut?",
      "hobbies": [
        "Reading",
        "Dancing",
        "Watching movies"
      ]
    },
    {
      "id": 4,
      "name": "Munmro Labus",
      "picture": "https://picsum.photos/200/300",
      "occupation": "Web Developer III",
      "likes": 39,
      "description": "Lorem ipsum dolor sit amet, consectetur adipisicing elit. Assumenda dolor labore ullam sapiente recusandae voluptatibus! Eligendi consequuntur nesciunt totam aut?",
      "hobbies": [
        "Reading",
        "Dancing",
        "Watching movies"
      ]
    },
    {
      "id": 5,
      "name": "Cornall McPaik",
      "picture": "https://picsum.photos/200/300",
      "occupation": "Research Associate",
      "likes": 28,
      "description": "Lorem ipsum dolor sit amet, consectetur adipisicing elit. Assumenda dolor labore ullam sapiente recusandae voluptatibus! Eligendi consequuntur nesciunt totam aut?",
      "hobbies": [
        "Reading",
        "Dancing",
        "Watching movies"
      ]
    },
    {
      "id": 6,
      "name": "Yale Dykas",
      "picture": "https://picsum.photos/200/300",
      "occupation": "Software Engineer II",
      "likes": 17,
      "description": "Lorem ipsum dolor sit amet, consectetur adipisicing elit. Assumenda dolor labore ullam sapiente recusandae voluptatibus! Eligendi consequuntur nesciunt totam aut?",
      "hobbies": [
        "Reading",
        "Dancing",
        "Watching movies"
      ]
    }
  ]
}